aetosky_job_processing
