Metadata-Version: 2.1
Name: aetosky_job_processing
Version: 1.0.3
Requires-Dist: requests
Requires-Dist: aiohttp
